<?xml version="1.0" encoding="utf-8"?>
<gpx version="1.0"><name>RestrictiiTrafic</name><desc>ZONA;GR-100;</desc><bounds minlat="44.1910670769837" minlon="24.3526189304734" maxlat="45.6459973168196" maxlon="25.4138323007244"/><trk><name>ruta</name><trkseg><trkpt lat="45.62870927953129" lon="25.008331955458363"><time>2021-07-06T11:58:04Z</time></trkpt><trkpt lat="45.589414749885115" lon="25.206459230201208"><time>2021-07-06T11:58:04Z</time></trkpt><trkpt lat="45.51208466408006" lon="25.31195631696904"><time>2021-07-06T11:58:04Z</time></trkpt><trkpt lat="45.4357453392449" lon="25.36207773093893"><time>2021-07-06T11:58:04Z</time></trkpt><trkpt lat="45.333336876798" lon="25.400335911981244"><time>2021-07-06T11:58:04Z</time></trkpt><trkpt lat="45.14191119938586" lon="25.279014774170985"><time>2021-07-06T11:58:04Z</time></trkpt><trkpt lat="45.07902788913438" lon="25.260535440988242"><time>2021-07-06T11:58:04Z</time></trkpt><trkpt lat="44.95914157926314" lon="25.35048600251168"><time>2021-07-06T11:58:04Z</time></trkpt><trkpt lat="44.834107956425754" lon="25.308214903175905"><time>2021-07-06T11:58:04Z</time></trkpt><trkpt lat="44.736882458338215" lon="25.309244871437624"><time>2021-07-06T11:58:04Z</time></trkpt><trkpt lat="44.535822426329844" lon="25.40902578216971"><time>2021-07-06T11:58:04Z</time></trkpt><trkpt lat="44.50987583980833" lon="25.413832300724397"><time>2021-07-06T11:58:04Z</time></trkpt><trkpt lat="44.41431251217735" lon="25.405981196088785"><time>2021-07-06T11:58:04Z</time></trkpt><trkpt lat="44.34706856102578" lon="25.322195012230306"><time>2021-07-06T11:58:04Z</time></trkpt><trkpt lat="44.35517004678652" lon="25.121694523949056"><time>2021-07-06T11:58:04Z</time></trkpt><trkpt lat="44.24323180691723" lon="24.91595435613591"><time>2021-07-06T11:58:04Z</time></trkpt><trkpt lat="44.191067076983664" lon="24.75012946599919"><time>2021-07-06T11:58:04Z</time></trkpt><trkpt lat="44.3183673682066" lon="24.659059987408994"><time>2021-07-06T11:58:04Z</time></trkpt><trkpt lat="44.39372938121551" lon="24.610651479108213"><time>2021-07-06T11:58:04Z</time></trkpt><trkpt lat="44.510063499330975" lon="24.643882011240332"><time>2021-07-06T11:58:04Z</time></trkpt><trkpt lat="44.606077526946414" lon="24.614572109122296"><time>2021-07-06T11:58:04Z</time></trkpt><trkpt lat="44.717992877130584" lon="24.514323947563298"><time>2021-07-06T11:58:04Z</time></trkpt><trkpt lat="44.799417405246885" lon="24.352618930473454"><time>2021-07-06T11:58:04Z</time></trkpt><trkpt lat="44.94112393340964" lon="24.383310508073958"><time>2021-07-06T11:58:04Z</time></trkpt><trkpt lat="45.13448034043013" lon="24.454721640886458"><time>2021-07-06T11:58:04Z</time></trkpt><trkpt lat="45.26789697213311" lon="24.408373069109114"><time>2021-07-06T11:58:04Z</time></trkpt><trkpt lat="45.43497206685578" lon="24.366755934266255"><time>2021-07-06T11:58:04Z</time></trkpt><trkpt lat="45.611184571320805" lon="24.486952619507896"><time>2021-07-06T11:58:04Z</time></trkpt><trkpt lat="45.64599731681961" lon="24.68230281337312"><time>2021-07-06T11:58:04Z</time></trkpt><trkpt lat="45.62923336993212" lon="25.000788984844327"><time>2021-07-06T11:58:04Z</time></trkpt></trkseg></trk></gpx>
